pycropwat/__init__.py
pycropwat/analysis.py
pycropwat/cli.py
pycropwat/core.py
pycropwat/methods.py
pycropwat/utils.py
pycropwat-1.2.dist-info/licenses/LICENSE
pycropwat-1.2.dist-info/METADATA
pycropwat-1.2.dist-info/WHEEL
pycropwat-1.2.dist-info/entry_points.txt
pycropwat-1.2.dist-info/top_level.txt
pycropwat-1.2.dist-info/RECORD
