Metadata-Version: 2.4
Name: pycropwat
Version: 1.2
Summary: A Python Package for Computing Effective Precipitation Using Google Earth Engine Climate Data
Author-email: Sayantan Majumdar <sayantan.majumdar@dri.edu>, Peter ReVelle <peter.revelle@dri.edu>, Christopher Pearson <christopher.pearson@dri.edu>, Soheil Nozari <soheil.nozari@colostate.edu>, "Blake A. Minor" <blake.minor@dri.edu>, "M. F. Hasan" <fahim.hasan@colostate.edu>, "Justin L. Huntington" <justin.huntington@dri.edu>, "Ryan G. Smith" <ryan.g.smith@colostate.edu>
License: MIT
Project-URL: Homepage, https://github.com/montimaj/pyCropWat
Project-URL: Documentation, https://montimaj.github.io/pyCropWat
Project-URL: Repository, https://github.com/montimaj/pyCropWat
Project-URL: Issues, https://github.com/montimaj/pyCropWat/issues
Keywords: earth-engine,precipitation,hydrology,cropwat,effective-precipitation,remote-sensing
Classifier: Development Status :: 3 - Alpha
Classifier: Intended Audience :: Science/Research
Classifier: License :: OSI Approved :: MIT License
Classifier: Operating System :: OS Independent
Classifier: Programming Language :: Python :: 3
Classifier: Programming Language :: Python :: 3.9
Classifier: Programming Language :: Python :: 3.10
Classifier: Programming Language :: Python :: 3.11
Classifier: Programming Language :: Python :: 3.12
Classifier: Topic :: Scientific/Engineering :: GIS
Classifier: Topic :: Scientific/Engineering :: Hydrology
Requires-Python: >=3.9
License-File: LICENSE
Requires-Dist: earthengine-api>=0.1.370
Requires-Dist: numpy>=1.21.0
Requires-Dist: xarray>=2022.3.0
Requires-Dist: rioxarray>=0.14.0
Requires-Dist: geopandas>=0.12.0
Requires-Dist: shapely>=2.0.0
Requires-Dist: dask>=2022.1.0
Requires-Dist: distributed>=2022.1.0
Requires-Dist: rasterio>=1.3.0
Requires-Dist: scipy>=1.9.0
Requires-Dist: matplotlib>=3.5.0
Requires-Dist: rasterstats>=0.18.0
Requires-Dist: pandas>=1.4.0
Requires-Dist: folium>=0.14.0
Requires-Dist: netCDF4>=1.6.0
Provides-Extra: interactive
Requires-Dist: leafmap>=0.30.0; extra == "interactive"
Requires-Dist: localtileserver>=0.7.0; extra == "interactive"
Provides-Extra: dev
Requires-Dist: pytest>=7.0.0; extra == "dev"
Requires-Dist: pytest-cov>=4.0.0; extra == "dev"
Requires-Dist: black>=23.0.0; extra == "dev"
Requires-Dist: ruff>=0.1.0; extra == "dev"
Provides-Extra: docs
Requires-Dist: mkdocs>=1.5.0; extra == "docs"
Requires-Dist: mkdocs-material>=9.0.0; extra == "docs"
Requires-Dist: mkdocstrings[python]>=0.24.0; extra == "docs"
Requires-Dist: mkdocs-gen-files>=0.5.0; extra == "docs"
Requires-Dist: mkdocs-literate-nav>=0.6.0; extra == "docs"
Requires-Dist: mkdocs-section-index>=0.3.0; extra == "docs"
Dynamic: license-file
